setup.cfg
setup.py
Graphtiny.egg-info/PKG-INFO
Graphtiny.egg-info/SOURCES.txt
Graphtiny.egg-info/dependency_links.txt
Graphtiny.egg-info/requires.txt
Graphtiny.egg-info/top_level.txt
graphtiny/__init__.py
graphtiny/api.py
graphtiny/domain.py
graphtiny/service.py
graphtiny/util.py